datadocket/__init__.py
datadocket/load/__init__.py
datadocket/load/main_load.py
datadocket/save/__init__.py
datadocket/save/main_save.py
datadocket/utils/__init__.py
datadocket/utils/main_utils.py
datadocket/zip/__init__.py
datadocket/zip/main_zip.py
datadocket-0.1.6.dist-info/licenses/LICENSE
datadocket-0.1.6.dist-info/METADATA
datadocket-0.1.6.dist-info/WHEEL
datadocket-0.1.6.dist-info/top_level.txt
datadocket-0.1.6.dist-info/RECORD
