Metadata-Version: 2.4
Name: datadocket
Version: 0.1.6
Summary: A simple data loading and saving utility library.
Author: Enric Grau-Luque
Author-email: egl.energy796@passmail.com
Requires-Python: >=3.6
License-File: LICENSE
Dynamic: author
Dynamic: author-email
Dynamic: license-file
Dynamic: requires-python
Dynamic: summary
